{
  "generated": "2025-12-10",
  "phase": "11-A",
  "index_files_checked": 5,
  "issues_found": 4,
  "results": [
    {
      "file": "docs/app-guidelines/INDEX.md",
      "status": "OK",
      "brokenLinks": [],
      "missingLinks": [],
      "notes": "Phase 10-C에서 업데이트 완료"
    },
    {
      "file": "docs/specs/INDEX.md",
      "status": "OK",
      "brokenLinks": [],
      "missingLinks": [],
      "notes": "Phase 9에서 업데이트 완료"
    },
    {
      "file": "docs/design/INDEX.md",
      "status": "NEEDS_UPDATE",
      "brokenLinks": [],
      "missingLinks": [
        "architecture/appstore-overview.md",
        "architecture/cms-overview.md",
        "architecture/extension-lifecycle.md",
        "architecture/module-loader-spec.md",
        "architecture/view-system.md"
      ],
      "notes": "Phase 10에서 생성된 5개 architecture 문서 누락"
    },
    {
      "file": "docs/reference/INDEX.md",
      "status": "NOT_CHECKED",
      "notes": "reference 디렉토리는 별도 검토 필요"
    },
    {
      "file": "docs/INDEX.md",
      "status": "NEEDS_UPDATE",
      "brokenLinks": [],
      "missingLinks": [
        "design/architecture/ 신규 문서들",
        "_analysis/ 디렉토리"
      ],
      "notes": "루트 INDEX 업데이트 필요"
    }
  ],
  "empty_placeholder_files": [
    {
      "file": "docs/specs/cosmetics/api-spec.md",
      "lines": 2,
      "action": "DELETE or FILL"
    },
    {
      "file": "docs/specs/cosmetics/extension-manifest.md",
      "lines": 2,
      "action": "DELETE or FILL"
    },
    {
      "file": "docs/specs/cosmetics/service-blueprint.md",
      "lines": 2,
      "action": "DELETE or FILL"
    },
    {
      "file": "docs/specs/cosmetics/ui-wireframes.md",
      "lines": 2,
      "action": "DELETE or FILL"
    }
  ],
  "recommendations": [
    {
      "priority": "HIGH",
      "action": "Update docs/design/INDEX.md to include 5 new architecture docs",
      "files_to_add": [
        "architecture/appstore-overview.md",
        "architecture/cms-overview.md",
        "architecture/extension-lifecycle.md",
        "architecture/module-loader-spec.md",
        "architecture/view-system.md"
      ]
    },
    {
      "priority": "MEDIUM",
      "action": "Delete empty placeholder files in specs/cosmetics/",
      "files_to_delete": [
        "api-spec.md",
        "extension-manifest.md",
        "service-blueprint.md",
        "ui-wireframes.md"
      ]
    },
    {
      "priority": "LOW",
      "action": "Update root docs/INDEX.md",
      "reason": "전체 구조 반영"
    }
  ]
}
